adafruit_circuitpython_funhouse-2.4.2.dist-info/licenses/LICENSE
adafruit_funhouse/__init__.py
adafruit_funhouse/graphics.py
adafruit_funhouse/network.py
adafruit_funhouse/peripherals.py
adafruit_circuitpython_funhouse-2.4.2.dist-info/METADATA
adafruit_circuitpython_funhouse-2.4.2.dist-info/WHEEL
adafruit_circuitpython_funhouse-2.4.2.dist-info/top_level.txt
adafruit_circuitpython_funhouse-2.4.2.dist-info/RECORD
