Metadata-Version: 2.4
Name: adafruit-circuitpython-funhouse
Version: 2.4.2
Summary: Helper library for the FunHouse board
Author-email: Adafruit Industries <circuitpython@adafruit.com>
License: MIT
Project-URL: Homepage, https://github.com/adafruit/Adafruit_CircuitPython_FunHouse
Keywords: adafruit,funhouse,microcontroller,sensors,hardware,micropythoncircuitpython
Classifier: Intended Audience :: Developers
Classifier: Topic :: Software Development :: Libraries
Classifier: Topic :: Software Development :: Embedded Systems
Classifier: Topic :: System :: Hardware
Classifier: License :: OSI Approved :: MIT License
Classifier: Programming Language :: Python :: 3
License-File: LICENSE
Requires-Dist: Adafruit-Blinka-displayio
Requires-Dist: Adafruit-Blinka
Requires-Dist: adafruit-circuitpython-ahtx0
Requires-Dist: adafruit-circuitpython-minimqtt
Requires-Dist: adafruit-circuitpython-dotstar
Requires-Dist: adafruit-circuitpython-requests
Requires-Dist: adafruit-circuitpython-simpleio
Requires-Dist: adafruit-circuitpython-portalbase
Requires-Dist: adafruit-circuitpython-dps310
Provides-Extra: optional
Dynamic: license-file
